quantum_avalanche/__init__.py
quantum_avalanche/quantum_avalanche.py
quantum_avalanche-0.1.0.dist-info/LICENSE
quantum_avalanche-0.1.0.dist-info/METADATA
quantum_avalanche-0.1.0.dist-info/WHEEL
quantum_avalanche-0.1.0.dist-info/top_level.txt
quantum_avalanche-0.1.0.dist-info/RECORD
