Metadata-Version: 2.1
Name: quantum-avalanche
Version: 0.1.0
Summary: A custom 256-bit hashing algorithm: QuantumAvalanche_256
Home-page: https://github.com/glidespace/quantum-avalanche
Author: GLIDE
Author-email: clehackweb@gmail.com
Classifier: Programming Language :: Python :: 3
Classifier: License :: OSI Approved :: MIT License
Classifier: Operating System :: OS Independent
Requires-Python: >=3.6
License-File: LICENSE
